pywerview/__init__.py
pywerview/formatters.py
pywerview/requester.py
pywerview/cli/__init__.py
pywerview/cli/helpers.py
pywerview/cli/main.py
pywerview/functions/__init__.py
pywerview/functions/gpo.py
pywerview/functions/hunting.py
pywerview/functions/misc.py
pywerview/functions/net.py
pywerview/objects/__init__.py
pywerview/objects/adobjects.py
pywerview/objects/rpcobjects.py
pywerview/worker/__init__.py
pywerview/worker/hunting.py
pywerview-0.7.3.dist-info/LICENSE
pywerview-0.7.3.dist-info/METADATA
pywerview-0.7.3.dist-info/WHEEL
pywerview-0.7.3.dist-info/entry_points.txt
pywerview-0.7.3.dist-info/top_level.txt
pywerview-0.7.3.dist-info/RECORD
