Metadata-Version: 2.2
Name: pywerview
Version: 0.7.3
Summary: A Python port of PowerSploit's PowerView
Author-email: Yannick Méheut <yannick@meheut.org>
License:                     GNU GENERAL PUBLIC LICENSE
Project-URL: homepage, https://github.com/the-useless-one/pywerview
Project-URL: repository, https://github.com/the-useless-one/pywerview
Keywords: python,powersploit,pentesting,recon,active,directory, windows
Classifier: Environment :: Console
Classifier: License :: OSI Approved :: GNU General Public License v3 or later (GPLv3+)
Classifier: Programming Language :: Python :: 3.6
Classifier: Topic :: Security
License-File: LICENSE
Requires-Dist: beautifulsoup4
Requires-Dist: lxml
Requires-Dist: pyasn1
Requires-Dist: ldap3-bleeding-edge
Requires-Dist: pycryptodome
Requires-Dist: impacket
Provides-Extra: kerberos
Requires-Dist: ldap3-bleeding-edge[kerberos]; extra == "kerberos"
